{
  "schemaVersion": 1,
  "guideId": "pokemon-crystal",
  "pass": "widget",
  "widget": {
    "id": "pokemon-crystal:enc-vermilion-city",
    "title": "Wild Encounters",
    "type": "dataTable",
    "scope": {
      "kind": "location",
      "locationId": "pokemon-crystal:vermilion-city"
    },
    "deckPosition": 2,
    "columns": [
      {
        "id": "sub-area",
        "label": "Sub-area"
      },
      {
        "id": "species",
        "label": "Species"
      },
      {
        "id": "levels",
        "label": "Levels"
      },
      {
        "id": "method",
        "label": "Method"
      },
      {
        "id": "rarity",
        "label": "Rarity"
      },
      {
        "id": "time",
        "label": "Time"
      }
    ],
    "rows": [
      {
        "checkable": false,
        "itemId": "pokemon-crystal:enc-vermilion-city:chinchou-good-rod-any",
        "cells": {
          "sub-area": "Vermilion City",
          "species": "Chinchou",
          "levels": "20",
          "method": "good-rod",
          "rarity": "20%",
          "time": "any"
        },
        "sourceRefs": [
          "src-serebii-pokearth"
        ],
        "confidence": "normal"
      },
      {
        "checkable": false,
        "itemId": "pokemon-crystal:enc-vermilion-city:chinchou-super-rod-any",
        "cells": {
          "sub-area": "Vermilion City",
          "species": "Chinchou",
          "levels": "40",
          "method": "super-rod",
          "rarity": "40%",
          "time": "any"
        },
        "sourceRefs": [
          "src-serebii-pokearth"
        ],
        "confidence": "normal"
      },
      {
        "checkable": false,
        "itemId": "pokemon-crystal:enc-vermilion-city:harbor-chinchou-good-rod-any",
        "cells": {
          "sub-area": "Harbor",
          "species": "Chinchou",
          "levels": "20",
          "method": "good-rod",
          "rarity": "20%",
          "time": "any"
        },
        "sourceRefs": [
          "src-serebii-pokearth"
        ],
        "confidence": "normal"
      },
      {
        "checkable": false,
        "itemId": "pokemon-crystal:enc-vermilion-city:harbor-chinchou-super-rod-any",
        "cells": {
          "sub-area": "Harbor",
          "species": "Chinchou",
          "levels": "40",
          "method": "super-rod",
          "rarity": "40%",
          "time": "any"
        },
        "sourceRefs": [
          "src-serebii-pokearth"
        ],
        "confidence": "normal"
      },
      {
        "checkable": false,
        "itemId": "pokemon-crystal:enc-vermilion-city:harbor-lanturn-super-rod-any",
        "cells": {
          "sub-area": "Harbor",
          "species": "Lanturn",
          "levels": "40",
          "method": "super-rod",
          "rarity": "10%",
          "time": "any"
        },
        "sourceRefs": [
          "src-serebii-pokearth"
        ],
        "confidence": "normal"
      },
      {
        "checkable": false,
        "itemId": "pokemon-crystal:enc-vermilion-city:harbor-magikarp-good-rod-any",
        "cells": {
          "sub-area": "Harbor",
          "species": "Magikarp",
          "levels": "20",
          "method": "good-rod",
          "rarity": "35%",
          "time": "any"
        },
        "sourceRefs": [
          "src-serebii-pokearth"
        ],
        "confidence": "normal"
      },
      {
        "checkable": false,
        "itemId": "pokemon-crystal:enc-vermilion-city:harbor-magikarp-old-rod-any",
        "cells": {
          "sub-area": "Harbor",
          "species": "Magikarp",
          "levels": "10",
          "method": "old-rod",
          "rarity": "85%",
          "time": "any"
        },
        "sourceRefs": [
          "src-serebii-pokearth"
        ],
        "confidence": "normal"
      },
      {
        "checkable": false,
        "itemId": "pokemon-crystal:enc-vermilion-city:harbor-shellder-good-rod-any",
        "cells": {
          "sub-area": "Harbor",
          "species": "Shellder",
          "levels": "20",
          "method": "good-rod",
          "rarity": "10%",
          "time": "any"
        },
        "sourceRefs": [
          "src-serebii-pokearth"
        ],
        "confidence": "normal"
      },
      {
        "checkable": false,
        "itemId": "pokemon-crystal:enc-vermilion-city:harbor-shellder-super-rod-any",
        "cells": {
          "sub-area": "Harbor",
          "species": "Shellder",
          "levels": "40",
          "method": "super-rod",
          "rarity": "30%",
          "time": "any"
        },
        "sourceRefs": [
          "src-serebii-pokearth"
        ],
        "confidence": "normal"
      },
      {
        "checkable": false,
        "itemId": "pokemon-crystal:enc-vermilion-city:harbor-tentacool-good-rod-any",
        "cells": {
          "sub-area": "Harbor",
          "species": "Tentacool",
          "levels": "20",
          "method": "good-rod",
          "rarity": "35%",
          "time": "any"
        },
        "sourceRefs": [
          "src-serebii-pokearth"
        ],
        "confidence": "normal"
      },
      {
        "checkable": false,
        "itemId": "pokemon-crystal:enc-vermilion-city:harbor-tentacool-old-rod-any",
        "cells": {
          "sub-area": "Harbor",
          "species": "Tentacool",
          "levels": "10",
          "method": "old-rod",
          "rarity": "15%",
          "time": "any"
        },
        "sourceRefs": [
          "src-serebii-pokearth"
        ],
        "confidence": "normal"
      },
      {
        "checkable": false,
        "itemId": "pokemon-crystal:enc-vermilion-city:harbor-tentacool-surf-any",
        "cells": {
          "sub-area": "Harbor",
          "species": "Tentacool",
          "levels": "30-39",
          "method": "surf",
          "rarity": "90%",
          "time": "any"
        },
        "sourceRefs": [
          "src-serebii-pokearth"
        ],
        "confidence": "normal"
      },
      {
        "checkable": false,
        "itemId": "pokemon-crystal:enc-vermilion-city:harbor-tentacruel-super-rod-any",
        "cells": {
          "sub-area": "Harbor",
          "species": "Tentacruel",
          "levels": "40",
          "method": "super-rod",
          "rarity": "20%",
          "time": "any"
        },
        "sourceRefs": [
          "src-serebii-pokearth"
        ],
        "confidence": "normal"
      },
      {
        "checkable": false,
        "itemId": "pokemon-crystal:enc-vermilion-city:harbor-tentacruel-surf-any",
        "cells": {
          "sub-area": "Harbor",
          "species": "Tentacruel",
          "levels": "35-39",
          "method": "surf",
          "rarity": "10%",
          "time": "any"
        },
        "sourceRefs": [
          "src-serebii-pokearth"
        ],
        "confidence": "normal"
      },
      {
        "checkable": false,
        "itemId": "pokemon-crystal:enc-vermilion-city:lanturn-super-rod-any",
        "cells": {
          "sub-area": "Vermilion City",
          "species": "Lanturn",
          "levels": "40",
          "method": "super-rod",
          "rarity": "10%",
          "time": "any"
        },
        "sourceRefs": [
          "src-serebii-pokearth"
        ],
        "confidence": "normal"
      },
      {
        "checkable": false,
        "itemId": "pokemon-crystal:enc-vermilion-city:magikarp-good-rod-any",
        "cells": {
          "sub-area": "Vermilion City",
          "species": "Magikarp",
          "levels": "20",
          "method": "good-rod",
          "rarity": "35%",
          "time": "any"
        },
        "sourceRefs": [
          "src-serebii-pokearth"
        ],
        "confidence": "normal"
      },
      {
        "checkable": false,
        "itemId": "pokemon-crystal:enc-vermilion-city:magikarp-old-rod-any",
        "cells": {
          "sub-area": "Vermilion City",
          "species": "Magikarp",
          "levels": "10",
          "method": "old-rod",
          "rarity": "85%",
          "time": "any"
        },
        "sourceRefs": [
          "src-serebii-pokearth"
        ],
        "confidence": "normal"
      },
      {
        "checkable": false,
        "itemId": "pokemon-crystal:enc-vermilion-city:shellder-good-rod-any",
        "cells": {
          "sub-area": "Vermilion City",
          "species": "Shellder",
          "levels": "20",
          "method": "good-rod",
          "rarity": "10%",
          "time": "any"
        },
        "sourceRefs": [
          "src-serebii-pokearth"
        ],
        "confidence": "normal"
      },
      {
        "checkable": false,
        "itemId": "pokemon-crystal:enc-vermilion-city:shellder-super-rod-any",
        "cells": {
          "sub-area": "Vermilion City",
          "species": "Shellder",
          "levels": "40",
          "method": "super-rod",
          "rarity": "30%",
          "time": "any"
        },
        "sourceRefs": [
          "src-serebii-pokearth"
        ],
        "confidence": "normal"
      },
      {
        "checkable": false,
        "itemId": "pokemon-crystal:enc-vermilion-city:tentacool-good-rod-any",
        "cells": {
          "sub-area": "Vermilion City",
          "species": "Tentacool",
          "levels": "20",
          "method": "good-rod",
          "rarity": "35%",
          "time": "any"
        },
        "sourceRefs": [
          "src-serebii-pokearth"
        ],
        "confidence": "normal"
      },
      {
        "checkable": false,
        "itemId": "pokemon-crystal:enc-vermilion-city:tentacool-old-rod-any",
        "cells": {
          "sub-area": "Vermilion City",
          "species": "Tentacool",
          "levels": "10",
          "method": "old-rod",
          "rarity": "15%",
          "time": "any"
        },
        "sourceRefs": [
          "src-serebii-pokearth"
        ],
        "confidence": "normal"
      },
      {
        "checkable": false,
        "itemId": "pokemon-crystal:enc-vermilion-city:tentacool-surf-any",
        "cells": {
          "sub-area": "Vermilion City",
          "species": "Tentacool",
          "levels": "30-39",
          "method": "surf",
          "rarity": "90%",
          "time": "any"
        },
        "sourceRefs": [
          "src-serebii-pokearth"
        ],
        "confidence": "normal"
      },
      {
        "checkable": false,
        "itemId": "pokemon-crystal:enc-vermilion-city:tentacruel-super-rod-any",
        "cells": {
          "sub-area": "Vermilion City",
          "species": "Tentacruel",
          "levels": "40",
          "method": "super-rod",
          "rarity": "20%",
          "time": "any"
        },
        "sourceRefs": [
          "src-serebii-pokearth"
        ],
        "confidence": "normal"
      },
      {
        "checkable": false,
        "itemId": "pokemon-crystal:enc-vermilion-city:tentacruel-surf-any",
        "cells": {
          "sub-area": "Vermilion City",
          "species": "Tentacruel",
          "levels": "35-39",
          "method": "surf",
          "rarity": "10%",
          "time": "any"
        },
        "sourceRefs": [
          "src-serebii-pokearth"
        ],
        "confidence": "normal"
      }
    ]
  }
}
